{
    "uuids": {
        "phone_id": "f7965140-6d3e-43df-841e-d9e3f56cb246",
        "uuid": "9e14a229-3f8e-40bf-902c-f969572ccc7e",
        "client_session_id": "62de5900-67c9-4128-a050-e2d05d48049f",
        "advertising_id": "abd41fd6-0ca4-4f79-92d3-17c2b574484e",
        "android_device_id": "android-4e0f392852b23941",
        "request_id": "aa6575f4-ff66-44ad-8eee-ba85eb38b63a",
        "tray_session_id": "d9a8e430-40d5-4107-b0d6-7c46a2856bfd"
    },
    "mid": "Z8uX4gABAAHPJ9Vlp0ftM-bCSary",
    "ig_u_rur": null,
    "ig_www_claim": null,
    "authorization_data": {},
    "cookies": {},
    "last_login": null,
    "device_settings": {
        "app_version": "269.0.0.18.75",
        "android_version": 26,
        "android_release": "8.0.0",
        "dpi": "480dpi",
        "resolution": "1080x1920",
        "manufacturer": "OnePlus",
        "device": "devitron",
        "model": "6T Dev",
        "cpu": "qcom",
        "version_code": "314665256"
    },
    "user_agent": "Instagram 269.0.0.18.75 Android (26/8.0.0; 480dpi; 1080x1920; OnePlus; 6T Dev; devitron; qcom; en_US; 314665256)",
    "country": "US",
    "country_code": 1,
    "locale": "en_US",
    "timezone_offset": -14400
}